MANIFEST.in
README.md
requirements.txt
setup.cfg
setup.py
html2txt/__init__.py
html2txt/converters/__init__.py
html2txt/converters/html2markdown.py
html2txt/parsers/__init__.py
html2txt/parsers/ast.py
html2txt/parsers/common.py
html2txt/parsers/etreehtmlparser.py
html2txt/parsers/parser.py
html2txt/parsers/visitor.py
html2txt/parsers/xmlfragmentparser.py
tests/test_00001_html2txt_9.py
tests/test_00002_html2txt_5.py
tests/test_00003_html2txt_15.py
tests/test_00004_html2txt_14.py
tests/test_00005_html2txt_4.py
tests/test_00006_html2txt_8.py
tests/test_00007_html2txt_3.py
tests/test_00008_html2txt_13.py
tests/test_00009_html2txt_12.py
tests/test_00010_html2txt_2.py
tests/test_00011_html2txt_11.py
tests/test_00012_html2txt_1.py
tests/test_00013_html2txt_10.py
tests/test_00014_html2txt_7.py
tests/test_00015_html2txt_6.py
tests/breakdance/LICENSE
tests/breakdance/expected/a-children.md
tests/breakdance/expected/base.md
tests/breakdance/expected/blockquote-markup.md
tests/breakdance/expected/blockquote-nested.md
tests/breakdance/expected/bootstrap-code.md
tests/breakdance/expected/bootstrap-css-checkmarks.md
tests/breakdance/expected/bootstrap-css-table.md
tests/breakdance/expected/bootstrap-css.md
tests/breakdance/expected/bootstrap-reboot-address.md
tests/breakdance/expected/bootstrap-reboot.md
tests/breakdance/expected/bootstrap-typeography.md
tests/breakdance/expected/breakdance.md
tests/breakdance/expected/caniuse-li-p.md
tests/breakdance/expected/caniuse.md
tests/breakdance/expected/code.md
tests/breakdance/expected/dl.html
tests/breakdance/expected/gfm-html.md
tests/breakdance/expected/gfm.md
tests/breakdance/expected/head-title.md
tests/breakdance/expected/head.md
tests/breakdance/expected/header1.md
tests/breakdance/expected/header2.md
tests/breakdance/expected/headings-inside-anchor.md
tests/breakdance/expected/headings-newlines.md
tests/breakdance/expected/headings-spacing.md
tests/breakdance/expected/hr.md
tests/breakdance/expected/list-li-code.md
