Metadata-Version: 2.1
Name: html2txt
Version: 0.6.0
Summary: Convert HTML to markdown
Home-page: https://github.com/renesugar/html2txt
Author: Rene Sugar
Author-email: rene.sugar@gmail.com
Maintainer: Rene Sugar
Maintainer-email: rene.sugar@gmail.com
License: MIT
Download-URL: https://github.com/renesugar/html2txt/tarball/master
Project-URL: Bug Tracker, https://github.com/renesugar/html2txt/issues
Project-URL: Documentation, https://github.com/renesugar/html2txt/wiki
Project-URL: Source Code, https://github.com/renesugar/html2txt
Keywords: markdown HTML converter ast
Platform: any
Classifier: Development Status :: 3 - Alpha
Classifier: Intended Audience :: Developers
Classifier: License :: OSI Approved :: MIT License
Classifier: Programming Language :: Python
Classifier: Programming Language :: Python :: 3.6
Classifier: Programming Language :: Python :: 3.7
Classifier: Operating System :: OS Independent
Classifier: Topic :: Software Development :: Libraries :: Python Modules
Classifier: Topic :: Software Development :: Documentation
Classifier: Topic :: Text Processing :: Filters
Classifier: Topic :: Text Processing :: Markup :: HTML
Requires-Python: >=3.6
